anabook/__init__.py
anabook/ad.py
anabook/clus.py
anabook/eda.py
anabook/edatest.py
anabook/edatestCategorical.py
anabook/edatestContinuos.py
anabook-1.42.dist-info/LICENSE
anabook-1.42.dist-info/METADATA
anabook-1.42.dist-info/WHEEL
anabook-1.42.dist-info/top_level.txt
anabook-1.42.dist-info/RECORD
