Metadata-Version: 2.1
Name: anabook
Version: 1.42
Summary: This library facilitates exploratory data analysis (EDA), streamlining access to key functions for univariate and bivariate analysis of continuous and categorical variables.
Home-page: https://github.com/FreddyAlvarado/anabook
Author: Freddy Alvarado
Author-email: freddy.alvarado.b1@gmail.com
License: MIT
Classifier: Programming Language :: Python :: 3
Classifier: License :: OSI Approved :: MIT License
Classifier: Operating System :: OS Independent
Classifier: Intended Audience :: Developers
Classifier: Intended Audience :: Science/Research
License-File: LICENSE
